fire_split/__init__.py
fire_split/_nbdev.py
fire_split/cli.py
fire_split/core.py
fire_split-0.1.9.dist-info/LICENSE
fire_split-0.1.9.dist-info/METADATA
fire_split-0.1.9.dist-info/WHEEL
fire_split-0.1.9.dist-info/entry_points.txt
fire_split-0.1.9.dist-info/top_level.txt
fire_split-0.1.9.dist-info/RECORD
